{
  "css/all.css": "css/all-c4b67c791f.css",
  "js/0.js": "js/0-1171c3b485.js",
  "js/1.js": "js/1-8b76423698.js",
  "js/all.js": "js/all-e63cc29173.js",
  "js/bundle.js": "js/bundle-117bd73d36.js",
  "js/iframeResizer.min.js": "js/iframeResizer-2eeddd0b6a.min.js",
  "js/vue-deps.js": "js/vue-deps-009275a3b7.js",
  "js/vue-form-builder.js": "js/vue-form-builder-26bd3a0d0a.js",
  "js/vue-milestone-competency-lists.js": "js/vue-milestone-competency-lists-2ca75258aa.js",
  "js/vue-reports.js": "js/vue-reports-d1e051a531.js",
  "js/vue-request.js": "js/vue-request-9486ad93de.js"
}